README.md
setup.py
custom_rails/__init__.py
custom_rails/__main__.py
custom_rails/app.py
custom_rails/cli.py
custom_rails/db.py
custom_rails/db_static.py
custom_rails/db_static_model.py
custom_rails/request.py
custom_rails/response.py
custom_rails/router.py
custom_rails/start_rails_app.py
custom_rails/template_gen.py
custom_rails.egg-info/PKG-INFO
custom_rails.egg-info/SOURCES.txt
custom_rails.egg-info/dependency_links.txt
custom_rails.egg-info/entry_points.txt
custom_rails.egg-info/top_level.txt
custom_rails/templates/config.ini
custom_rails/templates/main_app.py
custom_rails/templates/controllers/users.py
custom_rails/templates/controllers/__pycache__/posts.cpython-311.pyc
custom_rails/templates/db_models/user_model.py
custom_rails/templates/db_models/__pycache__/user_model.cpython-311.pyc
custom_rails/templates/helpers/my_helper.py
custom_rails/templates/helpers/__pycache__/my_helper.cpython-311.pyc
custom_rails/templates/styles/users.css
custom_rails/templates/views/users.html.jinja2
test/__init__.py
test/test_app.py
test/test_request.py
test/test_response.py
test/test_router.py
test/utils.py