Metadata-Version: 2.1
Name: custom-rails
Version: 0.0.9
Summary: An educational wsgi based python web framework
Maintainer: Patcas Rares
Keywords: wsgi,framework
Classifier: Development Status :: 3 - Alpha
Classifier: Environment :: Web Environment
Classifier: Programming Language :: Python :: 3
Classifier: Topic :: Internet :: WWW/HTTP
Classifier: Topic :: Software Development :: Libraries :: Python Modules
